scribble_to_epub/__init__.py
scribble_to_epub/__main__.py
scribble_to_epub/scribblehub.py
scribble_to_epub/assets/scribblehub.css
scribble_to_epub-0.0.4.dist-info/METADATA
scribble_to_epub-0.0.4.dist-info/WHEEL
scribble_to_epub-0.0.4.dist-info/entry_points.txt
scribble_to_epub-0.0.4.dist-info/licenses/LICENSE
scribble_to_epub-0.0.4.dist-info/RECORD
