Metadata-Version: 2.4
Name: scribble_to_epub
Version: 0.0.4
Summary: This scrapes books from https://www.scribblehub.com/ and  creates epub from them
Project-URL: Homepage, https://gitea.elara.ws/Hazel/scribble_to_epub
Project-URL: Issues, https://gitea.elara.ws/Hazel/scribble_to_epub/issues
License-File: LICENSE
Classifier: Operating System :: OS Independent
Classifier: Programming Language :: Python :: 3
Requires-Python: >=3.8
Requires-Dist: arrow~=1.3.0
Requires-Dist: beautifulsoup4~=4.13.4
Requires-Dist: cloudscraper
Requires-Dist: easy-requests~=0.0.1
Requires-Dist: ebooklib~=0.19
Requires-Dist: ftfy~=6.3.1
